sampledblib/__init__.py
sampledblib/app.py
sampledblib/file_manager.py
sampledblib/models.py
sampledblib-1.0.0.dist-info/WHEEL
sampledblib-1.0.0.dist-info/METADATA
sampledblib-1.0.0.dist-info/RECORD
